beetroots/__init__.py
beetroots/approx_optim/__init__.py
beetroots/approx_optim/abstract_approx_optim.py
beetroots/approx_optim/approach_type/__init__.py
beetroots/approx_optim/approach_type/abstract_approach_type.py
beetroots/approx_optim/approach_type/bo.py
beetroots/approx_optim/approach_type/utils.py
beetroots/approx_optim/forward_map/__init__.py
beetroots/approx_optim/forward_map/abstract_forward_map.py
beetroots/approx_optim/forward_map/nn.py
beetroots/approx_optim/forward_map/poly_reg.py
beetroots/approx_optim/nn_bo.py
beetroots/approx_optim/nn_bo_real_data.py
beetroots/approx_optim/nn_bo_toycase.py
beetroots/inversion/__init__.py
beetroots/inversion/plots/__init__.py
beetroots/inversion/plots/map_shaper.py
beetroots/inversion/plots/plots_2d.py
beetroots/inversion/plots/plots_2d_setup.py
beetroots/inversion/plots/plots_estimator.py
beetroots/inversion/plots/readable_line_names.py
beetroots/inversion/results/__init__.py
beetroots/inversion/results/abstract_results.py
beetroots/inversion/results/results_mcmc.py
beetroots/inversion/results/results_optim_map.py
beetroots/inversion/results/utils/__init__.py
beetroots/inversion/results/utils/abstract_util.py
beetroots/inversion/results/utils/bayes_pval_plots.py
beetroots/inversion/results/utils/clppd.py
beetroots/inversion/results/utils/ess_plots.py
beetroots/inversion/results/utils/kernel.py
beetroots/inversion/results/utils/lowest_obj_estimator.py
beetroots/inversion/results/utils/mc.py
beetroots/inversion/results/utils/mc_utils/__init__.py
beetroots/inversion/results/utils/mc_utils/ess.py
beetroots/inversion/results/utils/mc_utils/histograms.py
beetroots/inversion/results/utils/mmse_ci.py
beetroots/inversion/results/utils/objective.py
beetroots/inversion/results/utils/perf_saver.py
beetroots/inversion/results/utils/regularization_weights.py
beetroots/inversion/results/utils/valid_mc.py
beetroots/inversion/results/utils/y_f_Theta.py
beetroots/inversion/run/__init__.py
beetroots/inversion/run/abstract_run.py
beetroots-1.1.0.dist-info/AUTHORS.md
beetroots-1.1.0.dist-info/LICENSE
beetroots-1.1.0.dist-info/METADATA
beetroots-1.1.0.dist-info/WHEEL
beetroots-1.1.0.dist-info/RECORD
