Metadata-Version: 2.1
Name: beetroots
Version: 1.1.0
Summary: Beetroots (BayEsian infErence with spaTial Regularization of nOisy multi-line ObservaTion mapS)
Home-page: https://github.com/pierrePalud/beetroots
License: MIT
Keywords: Bayesian inference,statistics,artificial intelligence,multi-line maps,interstellar medium
Author: Pierre Palud
Requires-Python: >=3.9,<3.12
Classifier: Intended Audience :: Science/Research
Classifier: License :: OSI Approved :: MIT License
Classifier: Operating System :: OS Independent
Classifier: Programming Language :: Python :: 3
Classifier: Programming Language :: Python :: 3.9
Classifier: Programming Language :: Python :: 3.10
Classifier: Programming Language :: Python :: 3.11
Classifier: Topic :: Scientific/Engineering :: Mathematics
Classifier: Topic :: Software Development :: Libraries :: Python Modules
Provides-Extra: docs
Provides-Extra: notebook
Requires-Dist: Sphinx (>=5.3.0) ; extra == "docs"
Requires-Dist: bayesian-optimization (>=1.4.3)
Requires-Dist: cerberus (>=1.3.4)
Requires-Dist: click (>=8.0.4)
Requires-Dist: esbonio (>=0.15.0) ; extra == "docs"
Requires-Dist: flake8 (>=6.0.0)
Requires-Dist: h5py (>=3.6.0)
Requires-Dist: jupyter (>=1.0.0) ; extra == "notebook"
Requires-Dist: jupyter-lsp (>=2.2.2) ; extra == "notebook"
Requires-Dist: matplotlib (>=3.6.2)
Requires-Dist: myst_parser (>=1.0) ; extra == "docs"
Requires-Dist: nbsphinx (>=0.9.0) ; extra == "docs"
Requires-Dist: nbsphinx_link (>=1.0.0) ; extra == "docs"
Requires-Dist: nnbma (>=0.1.2)
Requires-Dist: notebook (>=7.0.7) ; extra == "notebook"
Requires-Dist: numba (>=0.54.1)
Requires-Dist: numpy (>=1.20.2)
Requires-Dist: pandas (>=1.3.4)
Requires-Dist: pre-commit (>=2.15.0)
Requires-Dist: rstcheck (>=6.1.1) ; extra == "docs"
Requires-Dist: scikit-learn (>=1.0.1)
Requires-Dist: scipy (>=1.11)
Requires-Dist: sphinx_design (>=0.1.0) ; extra == "docs"
Requires-Dist: sphinx_rtd_theme (>=1.2.0) ; extra == "docs"
Requires-Dist: sphinxcontrib-bibtex (>=2.6.0) ; extra == "docs"
Requires-Dist: torch (==2.2.1)
Requires-Dist: tqdm (>=4.62.3)
Project-URL: Bug Tracker, https://github.com/pierrePalud/beetroots/issues
Project-URL: Documentation, https://beetroots.readthedocs.io/en/latest/
Project-URL: Repository, https://github.com/pierrePalud/beetroots
